pap/__init__.py
pap/_author.py
pap/_version.py
pap-1.0.1.dist-info/DESCRIPTION.rst
pap-1.0.1.dist-info/METADATA
pap-1.0.1.dist-info/RECORD
pap-1.0.1.dist-info/WHEEL
pap-1.0.1.dist-info/entry_points.txt
pap-1.0.1.dist-info/metadata.json
pap-1.0.1.dist-info/top_level.txt
