Metadata-Version: 2.0
Name: pap
Version: 1.0.1
Summary: 
Requires-Dist: packaging
